[{"host":"aarch64-Linux","main":[{"name":"86box.AppImage","bin_name":"86box","description":"Emulator of x86-based machines (AppImage)","note":"You need to download ROMS (https://86box.readthedocs.io/en/latest/usage/roms.html)<br>(CI_VERIFIED: https://github.com/86Box/86Box/actions)","version":"v4.2.1","download_url":"https://pkg.ajam.dev/aarch64-Linux/86box.AppImage","size":"54.21 MB","bsum":"4a678c99c9e0aa7a2117a125b3bbfa1a6900a8319e55d1253bc13660ecb3ad65","shasum":"11ca18de866ea34c89255469e854aec6a82c93e6a407d2b32ffc9dd97d6efa13","build_date":"2024-10-09T14:03:41","src_url":"https://github.com/86Box/86Box","web_url":"https://86box.readthedocs.io","build_script":"https://github.com/Azathothas/Toolpacks-Extras/blob/main/.github/scripts/aarch64-Linux/pkgs/86box.sh","build_log":"https://pkg.ajam.dev/aarch64-Linux/86box.log","category":"emulator,hypervisor","extra_bins":""},{"name":"aisap.AppImage","bin_name":"aisap","description":"Tool to make sandboxing AppImages easy (AppImage | shImg)","note":"This PKG was built from Source using appimagetool (CI_VERIFIED: https://github.com/mgord9518/aisap/actions)","version":"v0.10.2-alpha","download_url":"https://pkg.ajam.dev/aarch64-Linux/aisap.AppImage","size":"2.5 MB","bsum":"4e7e49ab4c6b735d3d38f4eabcf03974da9533ffe868b09a8b84cb327538f0ac","shasum":"b22c967ee9bb07c02acc8574cafa1b36f772412b32f5282dad8d34a8fe9325fe","build_date":"2024-10-09T14:09:12","src_url":"https://github.com/mgord9518/aisap","web_url":"https://github.com/mgord9518/aisap","build_script":"https://github.com/Azathothas/Toolpacks-Extras/blob/main/.github/scripts/aarch64-Linux/pkgs/aisap.sh","build_log":"https://pkg.ajam.dev/aarch64-Linux/aisap.log","category":"cli,sandbox","extra_bins":"aisap.shimg"},{"name":"android-tools.AppImage","bin_name":"android-tools","description":"Android SDK Platform-Tools that interface with the Android platform, primarily adb and fastboot (AppImage)","note":"This PKG was built from Source using go-appimagetool, BUT the src has no CI (CI_VERIFIED: NONE)","version":"35.0.2","download_url":"https://pkg.ajam.dev/aarch64-Linux/android-tools.AppImage","size":"11.06 MB","bsum":"d9ada3d5a87a915325373034c3ea0ba8c62fa3fc5c6bec9a1954c1d63e1f506f","shasum":"f1b2e8100e9c986faad62e16389950dea86cc2aa8cd12d80ad64e782eb9a6b69","build_date":"2024-10-09T14:18:47","src_url":"https://github.com/lzhiyong/android-sdk-tools","web_url":"https://developer.android.com/tools/releases/platform-tools","build_script":"https://github.com/Azathothas/Toolpacks-Extras/blob/main/.github/scripts/aarch64-Linux/pkgs/android-tools.sh","build_log":"https://pkg.ajam.dev/aarch64-Linux/android-tools.log","category":"android,utility","extra_bins":""},{"name":"dunst.AppImage","bin_name":"dunst","description":"Lightweight and customizable notification daemon (AppImage)","note":"This PKG was built from Source using go-appimagetool","version":"1.11.0","download_url":"https://pkg.ajam.dev/aarch64-Linux/dunst.AppImage","size":"12.27 MB","bsum":"8f4b631af07eb7d85756ef433f5a40bb4906eaeb0bfe7182b60b30ab675a5b1b","shasum":"3805c1df2658191036f688c5a8d95bb4492f50453653f3f3565502a8ec5211d6","build_date":"2024-10-09T14:20:32","src_url":"https://github.com/dunst-project/dunst","web_url":"https://dunst-project.org","build_script":"https://github.com/Azathothas/Toolpacks-Extras/blob/main/.github/scripts/aarch64-Linux/pkgs/dunst.sh","build_log":"https://pkg.ajam.dev/aarch64-Linux/dunst.log","category":"daemon,notification","extra_bins":""},{"name":"floorp.NixAppImage","bin_name":"floorp","description":"A FireFox Fork with Advanced Features & More Customization (AppImage|NixAppImage)","note":"This PKG has Multiple Formats (CI_VERIFIED: https://github.com/Floorp-Projects/Floorp/actions)","version":"11.18.1","download_url":"https://pkg.ajam.dev/aarch64-Linux/floorp.NixAppImage","size":"355.41 MB","bsum":"5af4681b97e903fb11a3f19eacc96e463e9297dd64223952cc64232799b3c302","shasum":"946a7024220fa8231cf9eac81d8cf9f23913460065dae5da62c4b802b97c9d7a","build_date":"2024-10-09T14:24:11","src_url":"https://github.com/Floorp-Projects/Floorp","web_url":"https://floorp.app","build_script":"https://github.com/Azathothas/Toolpacks-Extras/blob/main/.github/scripts/aarch64-Linux/pkgs/floorp.sh","build_log":"https://pkg.ajam.dev/aarch64-Linux/floorp.log","category":"browser,firefox-fork","extra_bins":"floorp.AppImage"},{"name":"inkscape.NixAppImage","bin_name":"inkscape","description":"FOSS Vector Graphics Editor (AppImage|NixAppImage)","note":"This PKG has Multiple Formats (CI_VERIFIED: https://gitlab.com/inkscape/inkscape/-/pipelines)","version":"1.3.2","download_url":"https://pkg.ajam.dev/aarch64-Linux/inkscape.NixAppImage","size":"245.76 MB","bsum":"4475c365d2a3ae18d4ef55ed8d1d8527a8b7da7b48623bf187b6e9c623cee455","shasum":"cffef8d01945fded59ca8cb307c65da113e7b0fd51158f7fd6ed76e33b6542f7","build_date":"2024-10-09T14:25:53","src_url":"https://gitlab.com/inkscape/inkscape","web_url":"https://inkscape.org","build_script":"https://github.com/Azathothas/Toolpacks-Extras/blob/main/.github/scripts/aarch64-Linux/pkgs/inkscape.sh","build_log":"https://pkg.ajam.dev/aarch64-Linux/inkscape.log","category":"graphics,multimedia","extra_bins":"inkscape.AppImage,inkscape-dev.AppImage"},{"name":"librewolf.AppImage","bin_name":"librewolf","description":"LibreWolf Web Browser is a fork of Firefox, focused on privacy, security and freedom (AppImage|NixAppImage)","note":"This PKG has Multiple Formats (CI_VERIFIED: https://gitlab.com/librewolf-community/browser/appimage/-/pipelines)","version":"v131.0-1","download_url":"https://pkg.ajam.dev/aarch64-Linux/librewolf.AppImage","size":"88.39 MB","bsum":"3d2527a52f946d52363902de6343619804806e15775958c15c456403b7f6904e","shasum":"976f321ab387cc61484a7a2b78846bda0413dbcf38ae4a50986bcfc6dff2d993","build_date":"2024-10-09T14:26:11","src_url":"https://gitlab.com/librewolf-community/browser","web_url":"https://librewolf.net","build_script":"https://github.com/Azathothas/Toolpacks-Extras/blob/main/.github/scripts/aarch64-Linux/pkgs/librewolf.sh","build_log":"https://pkg.ajam.dev/aarch64-Linux/librewolf.log","category":"browser,privacy","extra_bins":"librewolf.NixAppImage"},{"name":"librewolf.NixAppImage","bin_name":"librewolf","description":"LibreWolf Web Browser is a fork of Firefox, focused on privacy, security and freedom (AppImage|NixAppImage)","note":"This PKG has Multiple Formats (CI_VERIFIED: https://gitlab.com/librewolf-community/browser/appimage/-/pipelines)","version":"130.0-3","download_url":"https://pkg.ajam.dev/aarch64-Linux/librewolf.NixAppImage","size":"334.29 MB","bsum":"c7719f370d3a2d308d4090683672cd8a6daab69df46c92bd9ac77249a85322d2","shasum":"4f52775b2bb28b826777f4472743df66ce91c6470206e8f62be7341b9734abce","build_date":"2024-10-09T14:27:52","src_url":"https://gitlab.com/librewolf-community/browser","web_url":"https://librewolf.net","build_script":"https://github.com/Azathothas/Toolpacks-Extras/blob/main/.github/scripts/aarch64-Linux/pkgs/librewolf.sh","build_log":"https://pkg.ajam.dev/aarch64-Linux/librewolf.log","category":"browser,privacy","extra_bins":"librewolf.AppImage"},{"name":"persepolis.NixAppImage","bin_name":"persepolis","description":"A Download Manager (GUI for aria2) written in Python (AppImage|NixAppImage)","note":"(CI_VERIFIED: NONE)","version":"4.0.1","download_url":"https://pkg.ajam.dev/aarch64-Linux/persepolis.NixAppImage","size":"214.37 MB","bsum":"5f18c8c863526a73b113946c6f392ead700b40496b1df0bfd3dcc6322c255b51","shasum":"fee58f531b3530254f607f4a42ed985e554cb7377027598fb9b069e8ddb4b194","build_date":"2024-10-09T14:29:13","src_url":"https://github.com/persepolisdm/persepolis","web_url":"https://persepolisdm.github.io","build_script":"https://github.com/Azathothas/Toolpacks-Extras/blob/main/.github/scripts/aarch64-Linux/pkgs/persepolis.sh","build_log":"https://pkg.ajam.dev/aarch64-Linux/persepolis.log","category":"downloader,multimedia","extra_bins":""},{"name":"ryujinx.AppImage","bin_name":"ryujinx","description":"A simple, experimental Nintendo Switch emulator","note":"(CI_VERIFIED: https://github.com/ryujinx-mirror/ryujinx/actions)","version":"r.b4cac89","download_url":"https://pkg.ajam.dev/aarch64-Linux/ryujinx.AppImage","size":"24.25 MB","bsum":"7c8419777f31562e3d9dd28520436ed7bbdc6999180e7c08cc1df0f87cb09f01","shasum":"78787c1a3f72592d887b08d883e672cabd1bb1b2173e5e5074d942b2d3104aff","build_date":"2024-10-09T14:29:58","src_url":"https://github.com/ryujinx-mirror/ryujinx","web_url":"https://github.com/ryujinx-mirror/ryujinx","build_script":"https://github.com/Azathothas/Toolpacks-Extras/blob/main/.github/scripts/aarch64-Linux/pkgs/ryujinx.sh","build_log":"https://pkg.ajam.dev/aarch64-Linux/ryujinx.log","category":"emulator","extra_bins":""}]},{"host":"x86_64-Linux","main":[{"name":"86box.AppImage","bin_name":"86box","description":"Emulator of x86-based machines (AppImage)","note":"You need to download ROMS (https://86box.readthedocs.io/en/latest/usage/roms.html)<br>(CI_VERIFIED: https://github.com/86Box/86Box/actions)","version":"v4.2.1","download_url":"https://pkg.ajam.dev/x86_64-Linux/86box.AppImage","size":"57.98 MB","bsum":"c74e70db214ef513427fd410a0bd5515f465582009bc68b478c550620f37c999","shasum":"dc7a4657bcd0a711f853a3fa23e0c398e861cfbe41238079e037cb6e275bc086","build_date":"2024-10-09T14:01:42","src_url":"https://github.com/86Box/86Box","web_url":"https://86box.readthedocs.io","build_script":"https://github.com/Azathothas/Toolpacks-Extras/blob/main/.github/scripts/x86_64-Linux/pkgs/86box.sh","build_log":"https://pkg.ajam.dev/x86_64-Linux/86box.log","category":"emulator,hypervisor","extra_bins":""},{"name":"acreom.AppImage","bin_name":"acreom","description":"An IDE based Knowledge Base using Markdown (AppImage)","note":"Closed Source<br>(CI_VERIFIED: NONE)","version":"v1.20.1","download_url":"https://pkg.ajam.dev/x86_64-Linux/acreom.AppImage","size":"139.07 MB","bsum":"bf30d35cddba5e409f11b1a13ced5152e27d28bde8edd29c8efc4faf163ee2c6","shasum":"0cb2d7541d0bd788e50e386fecbe2911a77e9a1e513f89100742de7e62d37d6d","build_date":"2024-10-09T14:02:06","src_url":"https://github.com/Acreom/releases","web_url":"https://acreom.com","build_script":"https://github.com/Azathothas/Toolpacks-Extras/blob/main/.github/scripts/x86_64-Linux/pkgs/acreom.sh","build_log":"https://pkg.ajam.dev/x86_64-Linux/acreom.log","category":"ide,knowledge-base,wiki","extra_bins":""},{"name":"actual.AppImage","bin_name":"actual","description":"A local-first personal finance app (AppImage)","note":"(CI_VERIFIED: https://github.com/actualbudget/actual/actions)","version":"v24.10.1","download_url":"https://pkg.ajam.dev/x86_64-Linux/actual.AppImage","size":"93.52 MB","bsum":"c2bc18ab656013adf2ebc255a70f0cae9fd795303e00ff4a87138aea0fab99e4","shasum":"65d6f275e6ba8b7016a0125775f268b6023336abffa3f5f5cb86a038f0be033d","build_date":"2024-10-09T14:02:21","src_url":"https://github.com/actualbudget/actual","web_url":"https://actualbudget.org","build_script":"https://github.com/Azathothas/Toolpacks-Extras/blob/main/.github/scripts/x86_64-Linux/pkgs/actual.sh","build_log":"https://pkg.ajam.dev/x86_64-Linux/actual.log","category":"finance","extra_bins":""},{"name":"advanced-passgen.AppImage","bin_name":"advanced-passgen","description":"Advanced Password Generator (AppImage)","note":"(CI_VERIFIED: https://github.com/CodeDead/Advanced-PassGen/actions)","version":"v2.5.2","download_url":"https://pkg.ajam.dev/x86_64-Linux/advanced-passgen.AppImage","size":"101.12 MB","bsum":"897d41eb5b4b8dbcef3bc8671f4bae9371c3c50b6a4afc0907e50483d77f37cb","shasum":"1f0e8ca2a37c539157fdc89437ea76804626c8b0928316bb1718149104c184e6","build_date":"2024-10-09T14:02:37","src_url":"https://github.com/CodeDead/Advanced-PassGen","web_url":"https://advancedpassgen.codedead.com","build_script":"https://github.com/Azathothas/Toolpacks-Extras/blob/main/.github/scripts/x86_64-Linux/pkgs/advanced-passgen.sh","build_log":"https://pkg.ajam.dev/x86_64-Linux/advanced-passgen.log","category":"passgen,password-manager","extra_bins":""},{"name":"affine.AppImage","bin_name":"affine","description":"Privacy-focused browser for Linux, macOS and Windows (AppImage|NixAppImage)","note":"This PKG has Multiple Formats (CI_VERIFIED: https://github.com/toeverything/AFFiNE/actions)","version":"v0.17.2","download_url":"https://pkg.ajam.dev/x86_64-Linux/affine.AppImage","size":"157.87 MB","bsum":"34a4d8cb82a6bcfc9e9cdaeac3122d3ba76ecf154ed8dc76cbed605caa817a17","shasum":"aef2f94c5a8ff4890761ff14f6a653f977fc27d78b7004ea0f21d49d524ceb2b","build_date":"2024-10-09T14:02:58","src_url":"https://github.com/toeverything/AFFiNE","web_url":"https://affine.pro","build_script":"https://github.com/Azathothas/Toolpacks-Extras/blob/main/.github/scripts/x86_64-Linux/pkgs/affine.sh","build_log":"https://pkg.ajam.dev/x86_64-Linux/affine.log","category":"knowledge-base,wiki","extra_bins":"affine.NixAppImage"},{"name":"aisap.AppImage","bin_name":"aisap","description":"Tool to make sandboxing AppImages easy (AppImage | shImg)","note":"This PKG was built from Source using appimagetool (CI_VERIFIED: https://github.com/mgord9518/aisap/actions)","version":"v0.10.2-alpha","download_url":"https://pkg.ajam.dev/x86_64-Linux/aisap.AppImage","size":"2.66 MB","bsum":"4c1e3b1aac577cd4d718c076d54ee425a914af9856eb26ddf726c5f6b4493b22","shasum":"ec28ff4bc413efd2326c30b0a48b41c2f50295e29bdb0a9fc9f668cdd0e656d0","build_date":"2024-10-09T14:11:09","src_url":"https://github.com/mgord9518/aisap","web_url":"https://github.com/mgord9518/aisap","build_script":"https://github.com/Azathothas/Toolpacks-Extras/blob/main/.github/scripts/x86_64-Linux/pkgs/aisap.sh","build_log":"https://pkg.ajam.dev/x86_64-Linux/aisap.log","category":"cli,sandbox","extra_bins":"aisap.shimg"},{"name":"aisap.shimg","bin_name":"aisap","description":"Tool to make sandboxing AppImages easy (AppImage | shImg)","note":"This PKG was built from Source using appimagetool (CI_VERIFIED: https://github.com/mgord9518/aisap/actions)","version":"latest","download_url":"https://pkg.ajam.dev/x86_64-Linux/aisap.shimg","size":"5.44 MB","bsum":"4264397461b74736dcefccbb326286dde41b24135a7e9fa949c6fa25a297aa1d","shasum":"f2460f95a37b59dbf6feda0f0cb4d5b22f650f67384b9bb401ede929047ff94f","build_date":"2024-10-09T14:33:12","src_url":"https://github.com/mgord9518/aisap","web_url":"https://github.com/mgord9518/aisap","build_script":"https://github.com/Azathothas/Toolpacks-Extras/blob/main/.github/scripts/x86_64-Linux/pkgs/aisap.sh","build_log":"https://pkg.ajam.dev/x86_64-Linux/aisap.log","category":"cli,sandbox","extra_bins":"aisap.AppImage"},{"name":"android-tools.AppImage","bin_name":"android-tools","description":"Android SDK Platform-Tools that interface with the Android platform, primarily adb and fastboot (AppImage)","note":"This PKG was built from Source using go-appimagetool","version":"35.0.2","download_url":"https://pkg.ajam.dev/x86_64-Linux/android-tools.AppImage","size":"7.21 MB","bsum":"c5c8b88ddc52c662b343e0bee3b7fa605311fde18b529cffff6c75b27b4bf36e","shasum":"d362d355c305183333d941c2d066717c24841f0654bf7c382b301422d52a7b27","build_date":"2024-10-09T14:17:11","src_url":"https://android.googlesource.com/platform/tools/base","web_url":"https://developer.android.com/tools/releases/platform-tools","build_script":"https://github.com/Azathothas/Toolpacks-Extras/blob/main/.github/scripts/x86_64-Linux/pkgs/android-tools.sh","build_log":"https://pkg.ajam.dev/x86_64-Linux/android-tools.log","category":"android,utility","extra_bins":""},{"name":"deadbeef-nightly.AppImage","bin_name":"deadbeef","description":"A Modular (Extensible with Plugins) Audio Player that can play & convert almost all Audio Formats (AppImage)","note":"This PKG was built from Portable Nightly Releases using AppImageTool<br>(CI_VERIFIED: https://github.com/DeaDBeeF-Player/deadbeef/actions)","version":"2024_09_07","download_url":"https://pkg.ajam.dev/x86_64-Linux/deadbeef-nightly.AppImage","size":"8.15 MB","bsum":"ef1988620ded51f6b082b901b38f28492fc12d4ca5d16b8525db29e5f7c0a10e","shasum":"4bd5e8e112c89dfc13937eada5068844f8dde9ba583954dd596b4c601308cd17","build_date":"2024-10-09T14:17:22","src_url":"https://github.com/DeaDBeeF-Player/deadbeef","web_url":"https://deadbeef.sourceforge.io","build_script":"https://github.com/Azathothas/Toolpacks-Extras/blob/main/.github/scripts/x86_64-Linux/pkgs/deadbeef-nightly.sh","build_log":"https://pkg.ajam.dev/x86_64-Linux/deadbeef-nightly.log","category":"multimedia,music,music-player","extra_bins":""},{"name":"deadbeef-stable.AppImage","bin_name":"deadbeef","description":"A Modular (Extensible with Plugins) Audio Player that can play & convert almost all Audio Formats (AppImage)","note":"This PKG was built from Portable Stable Releases using AppImageTool<br>(CI_VERIFIED: https://github.com/DeaDBeeF-Player/deadbeef/actions)","version":"1.9.6","download_url":"https://pkg.ajam.dev/x86_64-Linux/deadbeef-stable.AppImage","size":"8.15 MB","bsum":"8041335d1718329558064ca3f8284eb375952611225f124ce66d2a00cf4ff7ce","shasum":"3bad03b2b91eef2f5949ad3ddf0e6a21981813aea05254c8e3e8d71a9878ba7b","build_date":"2024-10-09T14:17:30","src_url":"https://github.com/DeaDBeeF-Player/deadbeef","web_url":"https://deadbeef.sourceforge.io","build_script":"https://github.com/Azathothas/Toolpacks-Extras/blob/main/.github/scripts/x86_64-Linux/pkgs/deadbeef-stable.sh","build_log":"https://pkg.ajam.dev/x86_64-Linux/deadbeef-stable.log","category":"multimedia,music,music-player","extra_bins":""},{"name":"dunst.AppImage","bin_name":"dunst","description":"Lightweight and customizable notification daemon (AppImage)","note":"This PKG was built from Source using go-appimagetool","version":"1.11.0","download_url":"https://pkg.ajam.dev/x86_64-Linux/dunst.AppImage","size":"12.92 MB","bsum":"8bd33c61dbca2f02554f09a155bf74e6a5d5282a4ab9127deb952dfb629234be","shasum":"cb1104c0f8def84b921d40c557845271866221f0f2a9fc27bbab67d7acf3d8b3","build_date":"2024-10-09T14:19:14","src_url":"https://github.com/dunst-project/dunst","web_url":"https://dunst-project.org","build_script":"https://github.com/Azathothas/Toolpacks-Extras/blob/main/.github/scripts/x86_64-Linux/pkgs/dunst.sh","build_log":"https://pkg.ajam.dev/x86_64-Linux/dunst.log","category":"daemon,notification","extra_bins":""},{"name":"floorp.NixAppImage","bin_name":"floorp","description":"A FireFox Fork with Advanced Features & More Customization (AppImage|NixAppImage)","note":"This PKG has Multiple Formats (CI_VERIFIED: https://github.com/Floorp-Projects/Floorp/actions)","version":"11.18.1","download_url":"https://pkg.ajam.dev/x86_64-Linux/floorp.NixAppImage","size":"366.35 MB","bsum":"58aa58539be247b137a5838899f9036f8a9c67ec5ac21bbc4b09e893a6738b00","shasum":"0fe86c240a22dedbaf5b9d510afc0fec1b3deabfe36d6a521c17bcdde2bc673d","build_date":"2024-10-09T14:20:57","src_url":"https://github.com/Floorp-Projects/Floorp","web_url":"https://floorp.app","build_script":"https://github.com/Azathothas/Toolpacks-Extras/blob/main/.github/scripts/x86_64-Linux/pkgs/floorp.sh","build_log":"https://pkg.ajam.dev/x86_64-Linux/floorp.log","category":"browser,firefox-fork","extra_bins":"floorp.AppImage"},{"name":"i3.AppImage","bin_name":"i3","description":"A Tiling Window Manager (AppImage|NixAppImage)","note":"This PKG has Multiple Formats<br>(CI_VERIFIED: https://github.com/i3/i3/actions)","version":"4.23","download_url":"https://pkg.ajam.dev/x86_64-Linux/i3.AppImage","size":"3.6 MB","bsum":"4a6f15cfa677b4c3d4484861ab188596e312611881717a83ccfb1e9064dcae14","shasum":"f655e78162513250b771fbc1be7156f34a7668bbf8ce897e290843b042eba664","build_date":"2024-10-09T14:21:03","src_url":"https://github.com/i3/i3","web_url":"https://i3wm.org","build_script":"https://github.com/Azathothas/Toolpacks-Extras/blob/main/.github/scripts/x86_64-Linux/pkgs/i3.sh","build_log":"https://pkg.ajam.dev/x86_64-Linux/i3.log","category":"window,window-manager,wm","extra_bins":"i3.NixAppImage"},{"name":"i3.NixAppImage","bin_name":"i3","description":"A Tiling Window Manager (AppImage|NixAppImage)","note":"This PKG has Multiple Formats<br>(CI_VERIFIED: https://github.com/i3/i3/actions)","version":"4.23","download_url":"https://pkg.ajam.dev/x86_64-Linux/i3.NixAppImage","size":"40.21 MB","bsum":"4a6d36403eab8f39f3d3e929a5498b30ed1f4c18eaecfe21c1db7ae0af91b3b7","shasum":"dc37052ec49c1da07764be6aa536591f931b571ea8d55497791c4e9662f02b2e","build_date":"2024-10-09T14:21:22","src_url":"https://github.com/i3/i3","web_url":"https://i3wm.org","build_script":"https://github.com/Azathothas/Toolpacks-Extras/blob/main/.github/scripts/x86_64-Linux/pkgs/i3.sh","build_log":"https://pkg.ajam.dev/x86_64-Linux/i3.log","category":"window,window-manager,wm","extra_bins":"i3.AppImage"},{"name":"inkscape.AppImage","bin_name":"inkscape","description":"FOSS Vector Graphics Editor (AppImage|NixAppImage)","note":"This PKG has Multiple Formats (CI_VERIFIED: https://gitlab.com/inkscape/inkscape/-/pipelines)","version":"1.3.2","download_url":"https://pkg.ajam.dev/x86_64-Linux/inkscape.AppImage","size":"96.33 MB","bsum":"b039b83a31c080d27a893f486bc3748a02b160f13f1a80a45852c800a78c9618","shasum":"999027bf1af436cf807eefe1250a95b4358798d9ecfbf08e4bec9dbe186e88cc","build_date":"2024-10-09T14:33:15","src_url":"https://gitlab.com/inkscape/inkscape","web_url":"https://inkscape.org","build_script":"https://github.com/Azathothas/Toolpacks-Extras/blob/main/.github/scripts/x86_64-Linux/pkgs/inkscape.sh","build_log":"https://pkg.ajam.dev/x86_64-Linux/inkscape.log","category":"graphics,multimedia","extra_bins":"inkscape-dev.AppImage,inkscape.NixAppImage"},{"name":"inkscape-dev.AppImage","bin_name":"inkscape","description":"FOSS Vector Graphics Editor (AppImage|NixAppImage)","note":"This PKG has Multiple Formats (CI_VERIFIED: https://gitlab.com/inkscape/inkscape/-/pipelines)","version":"67344e5-dev","download_url":"https://pkg.ajam.dev/x86_64-Linux/inkscape-dev.AppImage","size":"100.25 MB","bsum":"8d307dc6892bae792294e21987016d98f98e9b8b67eb7a3c6bf8af920a401f18","shasum":"acbb37d3930e5b7693ff3f2e5621d5a6e9cf62013d5efa1ecc9a4505dc344bc7","build_date":"2024-10-09T14:21:44","src_url":"https://gitlab.com/inkscape/inkscape","web_url":"https://inkscape.org","build_script":"https://github.com/Azathothas/Toolpacks-Extras/blob/main/.github/scripts/x86_64-Linux/pkgs/inkscape.sh","build_log":"https://pkg.ajam.dev/x86_64-Linux/inkscape.log","category":"graphics,multimedia","extra_bins":"inkscape.AppImage,inkscape.NixAppImage"},{"name":"inkscape.NixAppImage","bin_name":"inkscape","description":"FOSS Vector Graphics Editor (AppImage|NixAppImage)","note":"This PKG has Multiple Formats (CI_VERIFIED: https://gitlab.com/inkscape/inkscape/-/pipelines)","version":"1.3.2","download_url":"https://pkg.ajam.dev/x86_64-Linux/inkscape.NixAppImage","size":"253.96 MB","bsum":"7b2b8f1c08aeb182095f6402a0be3a7780d2925fd69869c68ff4e0978e4fbbb1","shasum":"f4ef8374ee896dcddd83a4ae13e9eb8db8d185c258e31bb76e67d238ef6702c2","build_date":"2024-10-09T14:23:29","src_url":"https://gitlab.com/inkscape/inkscape","web_url":"https://inkscape.org","build_script":"https://github.com/Azathothas/Toolpacks-Extras/blob/main/.github/scripts/x86_64-Linux/pkgs/inkscape.sh","build_log":"https://pkg.ajam.dev/x86_64-Linux/inkscape.log","category":"graphics,multimedia","extra_bins":"inkscape.AppImage,inkscape-dev.AppImage"},{"name":"librewolf.AppImage","bin_name":"librewolf","description":"LibreWolf Web Browser is a fork of Firefox, focused on privacy, security and freedom (AppImage|NixAppImage)","note":"This PKG has Multiple Formats (CI_VERIFIED: https://gitlab.com/librewolf-community/browser/appimage/-/pipelines)","version":"v131.0-1","download_url":"https://pkg.ajam.dev/x86_64-Linux/librewolf.AppImage","size":"93.93 MB","bsum":"9cc6476db8cdd33d076ce5e2179a59363e1c11d9084d33c40b124f99b190ab75","shasum":"53e22d25a590f69214737a61c3a771ca0c271862b439ab72e24b89e8b2c469e4","build_date":"2024-10-09T14:23:48","src_url":"https://gitlab.com/librewolf-community/browser","web_url":"https://librewolf.net","build_script":"https://github.com/Azathothas/Toolpacks-Extras/blob/main/.github/scripts/x86_64-Linux/pkgs/librewolf.sh","build_log":"https://pkg.ajam.dev/x86_64-Linux/librewolf.log","category":"browser,privacy","extra_bins":"librewolf.NixAppImage"},{"name":"librewolf.NixAppImage","bin_name":"librewolf","description":"LibreWolf Web Browser is a fork of Firefox, focused on privacy, security and freedom (AppImage|NixAppImage)","note":"This PKG has Multiple Formats (CI_VERIFIED: https://gitlab.com/librewolf-community/browser/appimage/-/pipelines)","version":"130.0-3","download_url":"https://pkg.ajam.dev/x86_64-Linux/librewolf.NixAppImage","size":"344.58 MB","bsum":"31eaf890cce1a968f5e34702ef77213a7be405ffb5025fb75c8a33c42b073f07","shasum":"0520d1a81c8b3f192fc5960496feb6b59fe1c023adf3736c68bfbf4ed252ac57","build_date":"2024-10-09T14:25:26","src_url":"https://gitlab.com/librewolf-community/browser","web_url":"https://librewolf.net","build_script":"https://github.com/Azathothas/Toolpacks-Extras/blob/main/.github/scripts/x86_64-Linux/pkgs/librewolf.sh","build_log":"https://pkg.ajam.dev/x86_64-Linux/librewolf.log","category":"browser,privacy","extra_bins":"librewolf.AppImage"},{"name":"mullvad-browser.NixAppImage","bin_name":"mullvad-browser","description":"Privacy-focused browser for Linux, macOS and Windows (Archive|AppImage|NixAppImage)","note":"This PKG has Multiple Formats (CI_VERIFIED: https://gitlab.torproject.org/tpo/applications/mullvad-browser/-/pipelines)","version":"13.5.6","download_url":"https://pkg.ajam.dev/x86_64-Linux/mullvad-browser.NixAppImage","size":"364.04 MB","bsum":"47cefb60b63e03d8390322d4c15881636198f375dcfdf37bd727c5369499c14f","shasum":"02713ca4c08b514a6cfa01f4bf2cfc5f26d34132e956d8f7c9bc3ae093e0e766","build_date":"2024-10-09T14:27:11","src_url":"https://gitlab.torproject.org/tpo/applications/mullvad-browser/","web_url":"https://mullvad.net/en/browser","build_script":"https://github.com/Azathothas/Toolpacks-Extras/blob/main/.github/scripts/x86_64-Linux/pkgs/mullvad-browser.sh","build_log":"https://pkg.ajam.dev/x86_64-Linux/mullvad-browser.log","category":"anonymity,browser,privacy,tor","extra_bins":"mullvad-browser.tar.xz"},{"name":"mullvad-browser.tar.xz","bin_name":"mullvad-browser","description":"Privacy-focused browser for Linux, macOS and Windows (Archive|AppImage|NixAppImage)","note":"This PKG has Multiple Formats (CI_VERIFIED: https://gitlab.torproject.org/tpo/applications/mullvad-browser/-/pipelines)","version":"13.5.6","download_url":"https://pkg.ajam.dev/x86_64-Linux/mullvad-browser.tar.xz","size":"103.44 MB","bsum":"ba7625379e99fb76abff48994196cb0325821edde8afd99f6ba971fc92e69fd8","shasum":"01ac865857ec7402bd2aee09e270e8949c67427d078467997847ffffd3aca560","build_date":"2024-10-09T14:25:31","src_url":"https://gitlab.torproject.org/tpo/applications/mullvad-browser/","web_url":"https://mullvad.net/en/browser","build_script":"https://github.com/Azathothas/Toolpacks-Extras/blob/main/.github/scripts/x86_64-Linux/pkgs/mullvad-browser.sh","build_log":"https://pkg.ajam.dev/x86_64-Linux/mullvad-browser.log","category":"anonymity,browser,privacy,tor","extra_bins":"mullvad-browser.NixAppImage"},{"name":"obs-studio.AppImage","bin_name":"obs-studio","description":"FOSS cross-platform screencasting and streaming app (AppImage|NixAppImage)","note":"This PKG has Multiple Formats (CI_VERIFIED: https://github.com/obsproject/obs-studio/actions)","version":"30.2.1","download_url":"https://pkg.ajam.dev/x86_64-Linux/obs-studio.AppImage","size":"178.81 MB","bsum":"189e09809e199d8fdf112eb1cc2d164898277adcf7dc835482c409d67dc08b3a","shasum":"35f399a854d65146035b4a57b5dd2b9e3d7bb457f8b5a5a89fe74370fc751f73","build_date":"2024-10-09T14:27:46","src_url":"https://github.com/obsproject/obs-studio","web_url":"https://obsproject.com","build_script":"https://github.com/Azathothas/Toolpacks-Extras/blob/main/.github/scripts/x86_64-Linux/pkgs/obs-studio.sh","build_log":"https://pkg.ajam.dev/x86_64-Linux/obs-studio.log","category":"multimedia,screenrecording,video","extra_bins":"obs-studio.NixAppImage"},{"name":"olive-editor.AppImage","bin_name":"olive","description":"Free open-source non-linear video editor (AppImage|NixAppImage)","note":"This PKG has Multiple Formats (CI_VERIFIED: https://github.com/olive-editor/olive/actions)","version":"2024-08-24T22:35:10Z","download_url":"https://pkg.ajam.dev/x86_64-Linux/olive-editor.AppImage","size":"120.54 MB","bsum":"31946c732fcdd9d4713e9b96d25da2e2999a6f792f986f3ed3723f178c799cec","shasum":"e75af6098b238238d85f4c7223bd874686c44c1c73d58bfb6911cf7fdf7c4843","build_date":"2024-10-09T14:28:21","src_url":"https://github.com/olive-editor/olive","web_url":"https://www.olivevideoeditor.org","build_script":"https://github.com/Azathothas/Toolpacks-Extras/blob/main/.github/scripts/x86_64-Linux/pkgs/olive-editor.sh","build_log":"https://pkg.ajam.dev/x86_64-Linux/olive-editor.log","category":"multimedia,video,video-editor","extra_bins":"olive-editor.NixAppImage"},{"name":"persepolis.NixAppImage","bin_name":"persepolis","description":"A Download Manager (GUI for aria2) written in Python (AppImage|NixAppImage)","note":"(CI_VERIFIED: NONE)","version":"4.0.1","download_url":"https://pkg.ajam.dev/x86_64-Linux/persepolis.NixAppImage","size":"222.3 MB","bsum":"63f47f0be74dc3365b7c0555d987a54a707b1e1b5dfc7664a28559eef52c0f18","shasum":"bd587a1f5dab3ee866b49fc30b91400e3e59e25a41e1970378f57d378712df33","build_date":"2024-10-09T14:29:31","src_url":"https://github.com/persepolisdm/persepolis","web_url":"https://persepolisdm.github.io","build_script":"https://github.com/Azathothas/Toolpacks-Extras/blob/main/.github/scripts/x86_64-Linux/pkgs/persepolis.sh","build_log":"https://pkg.ajam.dev/x86_64-Linux/persepolis.log","category":"downloader,multimedia","extra_bins":""},{"name":"puddletag.NixAppImage","bin_name":"puddletag","description":"Powerful, simple, audio tag editor for GNU/Linux (NixAppImage)","note":"(CI_VERIFIED: https://github.com/puddletag/puddletag/actions)","version":"2.3.0","download_url":"https://pkg.ajam.dev/x86_64-Linux/puddletag.NixAppImage","size":"210.37 MB","bsum":"9c8a853aedc387817efabfab22cea63be56a65e0fecc2029a3a605c2b760c236","shasum":"399f8909c9a37aa0276d1238d299ea67ab366dfe1ce7f3d81c4b14ef37553de1","build_date":"2024-10-09T14:30:37","src_url":"https://github.com/puddletag/puddletag","web_url":"https://docs.puddletag.net","build_script":"https://github.com/Azathothas/Toolpacks-Extras/blob/main/.github/scripts/x86_64-Linux/pkgs/puddletag.sh","build_log":"https://pkg.ajam.dev/x86_64-Linux/puddletag.log","category":"audio,multimedia,music","extra_bins":""},{"name":"qbittorrent-enhanced.AppImage","bin_name":"qbittorrent-enhanced","description":"A qBittorrent for with Enhanced Features (AppImage)","note":"(CI_VERIFIED: https://github.com/c0re100/qBittorrent-Enhanced-Edition/actions)","version":"release-4.6.7.10","download_url":"https://pkg.ajam.dev/x86_64-Linux/qbittorrent-enhanced.AppImage","size":"24.91 MB","bsum":"5a07396972a9366ebaeab5b7d670c3149b9eb407767d3bed135acdfdeff257c8","shasum":"656b2b7a8b274229d4943fe33ebcf9f5a2df31016611ad53ae993fb8bd9c5a45","build_date":"2024-10-09T14:33:12","src_url":"https://github.com/c0re100/qBittorrent-Enhanced-Edition","web_url":"https://github.com/c0re100/qBittorrent-Enhanced-Edition","build_script":"https://github.com/Azathothas/Toolpacks-Extras/blob/main/.github/scripts/x86_64-Linux/pkgs/qbittorrent-enhanced.sh","build_log":"https://pkg.ajam.dev/x86_64-Linux/qbittorrent-enhanced.log","category":"downloader,torrent","extra_bins":""},{"name":"qbittorrent.AppImage","bin_name":"qbittorrent","description":"A qBittorrent for with Enhanced Features (AppImage)","note":"This PKG has Multiple Formats (CI_VERIFIED: https://github.com/qbittorrent/qBittorrent/actions)","version":"5.0.0","download_url":"https://pkg.ajam.dev/x86_64-Linux/qbittorrent.AppImage","size":"84.37 MB","bsum":"aa6a9f6d0960fde933c041b1d217801e9408e4d8b470e047c8a784e5397f43d6","shasum":"0d76cd2943899ce651c05fc211124095edfd7796578020a544a7681698d2715f","build_date":"2024-10-09T14:31:51","src_url":"https://github.com/qbittorrent/qBittorrent","web_url":"https://www.qbittorrent.org","build_script":"https://github.com/Azathothas/Toolpacks-Extras/blob/main/.github/scripts/x86_64-Linux/pkgs/qbittorrent.sh","build_log":"https://pkg.ajam.dev/x86_64-Linux/qbittorrent.log","category":"downloader,torrent","extra_bins":"qbittorrent.NixAppImage"},{"name":"qbittorrent.NixAppImage","bin_name":"qbittorrent","description":"A qBittorrent for with Enhanced Features (AppImage)","note":"This PKG has Multiple Formats (CI_VERIFIED: https://github.com/qbittorrent/qBittorrent/actions)","version":"5.0.0","download_url":"https://pkg.ajam.dev/x86_64-Linux/qbittorrent.NixAppImage","size":"171.25 MB","bsum":"dd1bc3f373e67e0082a27f2276c62835d0ea7fdfc3e614d212b404b8fa17554b","shasum":"365d470816ccf3657e211ba828cfa723280eb7064239594353da43bb353e7fa2","build_date":"2024-10-09T14:32:49","src_url":"https://github.com/qbittorrent/qBittorrent","web_url":"https://www.qbittorrent.org","build_script":"https://github.com/Azathothas/Toolpacks-Extras/blob/main/.github/scripts/x86_64-Linux/pkgs/qbittorrent.sh","build_log":"https://pkg.ajam.dev/x86_64-Linux/qbittorrent.log","category":"downloader,torrent","extra_bins":"qbittorrent.AppImage"},{"name":"ryujinx.AppImage","bin_name":"ryujinx","description":"A simple, experimental Nintendo Switch emulator","note":"(CI_VERIFIED: https://github.com/ryujinx-mirror/ryujinx/actions)","version":"r.b4cac89","download_url":"https://pkg.ajam.dev/x86_64-Linux/ryujinx.AppImage","size":"25.24 MB","bsum":"14209892b072f41cb41644a88c364be454ced3206a6443a85dd1e9f2dbcfc7cc","shasum":"07cdeeb754eaa88fea83b4af9b681f0d442886948af27c2ac8b2913a90363a66","build_date":"2024-10-09T14:32:56","src_url":"https://github.com/ryujinx-mirror/ryujinx","web_url":"https://github.com/ryujinx-mirror/ryujinx","build_script":"https://github.com/Azathothas/Toolpacks-Extras/blob/main/.github/scripts/x86_64-Linux/pkgs/ryujinx.sh","build_log":"https://pkg.ajam.dev/x86_64-Linux/ryujinx.log","category":"emulator","extra_bins":""}]}]
